python_mcp_eddie/__init__.py
python_mcp_eddie/main.py
python_mcp_eddie-0.1.5.dist-info/METADATA
python_mcp_eddie-0.1.5.dist-info/WHEEL
python_mcp_eddie-0.1.5.dist-info/entry_points.txt
python_mcp_eddie-0.1.5.dist-info/RECORD
