Metadata-Version: 2.4
Name: python-mcp-eddie
Version: 0.1.5
Summary: This is sample mcp for me to use
License: MIT
Keywords: fastapi,mcp,python-mcp,sample
Classifier: Programming Language :: Python :: 3
Requires-Python: >=3.12
Requires-Dist: httpx>=0.28.1
Requires-Dist: mcp[cli]>=1.6.0
